linopy/__init__.py
linopy/base.py
linopy/common.py
linopy/config.py
linopy/constants.py
linopy/constraints.py
linopy/examples.py
linopy/expressions.py
linopy/io.py
linopy/matrices.py
linopy/model.py
linopy/monkey_patch_xarray.py
linopy/objective.py
linopy/py.typed
linopy/solver_capabilities.py
linopy/solvers.py
linopy/testing.py
linopy/types.py
linopy/variables.py
linopy/version.py
linopy/remote/__init__.py
linopy/remote/oetc.py
linopy/remote/ssh.py
linopy-0.6.1.dist-info/licenses/LICENSE.txt
linopy-0.6.1.dist-info/METADATA
linopy-0.6.1.dist-info/WHEEL
linopy-0.6.1.dist-info/top_level.txt
linopy-0.6.1.dist-info/RECORD
