Metadata-Version: 2.4
Name: linopy
Version: 0.6.1
Summary: Linear optimization with N-D labeled arrays in Python
Author-email: Fabian Hofmann <fabianmarikhofmann@gmail.com>
Project-URL: Homepage, https://github.com/PyPSA/linopy
Project-URL: Source, https://github.com/PyPSA/linopy
Classifier: Programming Language :: Python :: 3.10
Classifier: Programming Language :: Python :: 3.11
Classifier: Programming Language :: Python :: 3.12
Classifier: Programming Language :: Python :: 3.13
Classifier: Development Status :: 3 - Alpha
Classifier: Environment :: Console
Classifier: Intended Audience :: Science/Research
Classifier: License :: OSI Approved :: MIT License
Classifier: Natural Language :: English
Classifier: Typing :: Typed
Classifier: Operating System :: OS Independent
Requires-Python: >=3.10
License-File: LICENSE.txt
Requires-Dist: numpy; python_version > "3.10"
Requires-Dist: numpy<2; python_version <= "3.10"
Requires-Dist: scipy
Requires-Dist: bottleneck
Requires-Dist: toolz
Requires-Dist: numexpr
Requires-Dist: xarray>=2024.2.0
Requires-Dist: dask>=0.18.0
Requires-Dist: polars
Requires-Dist: tqdm
Requires-Dist: deprecation
Requires-Dist: packaging
Requires-Dist: google-cloud-storage
Requires-Dist: requests
Provides-Extra: docs
Requires-Dist: ipython==8.26.0; extra == "docs"
Requires-Dist: numpydoc==1.7.0; extra == "docs"
Requires-Dist: sphinx==7.3.7; extra == "docs"
Requires-Dist: sphinx_rtd_theme==2.0.0; extra == "docs"
Requires-Dist: sphinx_book_theme==1.1.3; extra == "docs"
Requires-Dist: nbsphinx==0.9.4; extra == "docs"
Requires-Dist: nbsphinx-link==1.3.0; extra == "docs"
Requires-Dist: docutils<0.21; extra == "docs"
Requires-Dist: numpy<2; extra == "docs"
Requires-Dist: gurobipy==11.0.2; extra == "docs"
Requires-Dist: ipykernel==6.29.5; extra == "docs"
Requires-Dist: matplotlib==3.9.1; extra == "docs"
Requires-Dist: highspy>=1.7.1; extra == "docs"
Provides-Extra: dev
Requires-Dist: pytest; extra == "dev"
Requires-Dist: pytest-cov; extra == "dev"
Requires-Dist: mypy; extra == "dev"
Requires-Dist: pre-commit; extra == "dev"
Requires-Dist: netcdf4; extra == "dev"
Requires-Dist: paramiko; extra == "dev"
Requires-Dist: types-paramiko; extra == "dev"
Requires-Dist: types-requests; extra == "dev"
Requires-Dist: gurobipy; extra == "dev"
Requires-Dist: highspy; extra == "dev"
Provides-Extra: solvers
Requires-Dist: gurobipy; extra == "solvers"
Requires-Dist: highspy>=1.5.0; python_version < "3.12" and extra == "solvers"
Requires-Dist: highspy>=1.7.1; python_version >= "3.12" and extra == "solvers"
Requires-Dist: cplex; (platform_system != "Darwin" and python_version < "3.12") and extra == "solvers"
Requires-Dist: mosek; extra == "solvers"
Requires-Dist: mindoptpy; python_version < "3.12" and extra == "solvers"
Requires-Dist: coptpy!=7.2.1; extra == "solvers"
Requires-Dist: xpress; (platform_system != "Darwin" and python_version < "3.11") and extra == "solvers"
Requires-Dist: pyscipopt; platform_system != "Darwin" and extra == "solvers"
Dynamic: license-file
